{"359": {"acronym": "F1_(4)", "name": "agranular frontal area F1 (or area 4)", "color_hex_triplet": "2D3AB7", "file_count": 447, "dandiset_count": 1, "dandisets": ["001636"], "total_file_count": 447, "total_dandiset_count": 1, "total_dandisets": ["001636"]}, "7": {"acronym": "SNpc", "name": "substantia nigra pars compacta", "color_hex_triplet": "B7552D", "file_count": 9, "dandiset_count": 1, "dandisets": ["001693"], "total_file_count": 9, "total_dandiset_count": 1, "total_dandisets": ["001693"]}, "317": {"acronym": "CA1", "name": "CA1 subfield of hippocampus", "color_hex_triplet": "912DB7", "file_count": 1, "dandiset_count": 1, "dandisets": ["000717"], "total_file_count": 1, "total_dandiset_count": 1, "total_dandisets": ["000717"]}, "5": {"acronym": "GPi", "name": "globus pallidus internal segment", "color_hex_triplet": "B7752D", "file_count": 37, "dandiset_count": 1, "dandisets": ["000947"], "total_file_count": 37, "total_dandiset_count": 1, "total_dandisets": ["000947"]}, "4": {"acronym": "GPe", "name": "globus pallidus external segment", "color_hex_triplet": "B7492D", "file_count": 6, "dandiset_count": 1, "dandisets": ["000947"], "total_file_count": 6, "total_dandiset_count": 1, "total_dandisets": ["000947"]}, "318": {"acronym": "V4", "name": "visual area 4 (dorsal part)", "color_hex_triplet": "2D40B7", "file_count": 100, "dandiset_count": 2, "dandisets": ["001357", "001358"], "total_file_count": 100, "total_dandiset_count": 2, "total_dandisets": ["001357", "001358"]}, "10007": {"acronym": "Cortex", "name": "Cortex", "color_hex_triplet": "3F7FBF", "file_count": 0, "dandiset_count": 0, "dandisets": [], "total_file_count": 547, "total_dandiset_count": 3, "total_dandisets": ["001357", "001358", "001636"]}, "9999": {"acronym": "root", "name": "D99 Atlas", "color_hex_triplet": "FFFFFF", "file_count": 0, "dandiset_count": 0, "dandisets": [], "total_file_count": 600, "total_dandiset_count": 6, "total_dandisets": ["000717", "000947", "001357", "001358", "001636", "001693"]}, "10100": {"acronym": "Nigral_region", "name": "Nigral region", "color_hex_triplet": "C55252", "file_count": 0, "dandiset_count": 0, "dandisets": [], "total_file_count": 9, "total_dandiset_count": 1, "total_dandisets": ["001693"]}, "10003": {"acronym": "Basal_ganglia", "name": "Basal ganglia", "color_hex_triplet": "BF3F3F", "file_count": 0, "dandiset_count": 0, "dandisets": [], "total_file_count": 52, "total_dandiset_count": 2, "total_dandisets": ["000947", "001693"]}, "10009": {"acronym": "Hippocampus", "name": "Hippocampus", "color_hex_triplet": "3F3FBF", "file_count": 0, "dandiset_count": 0, "dandisets": [], "total_file_count": 1, "total_dandiset_count": 1, "total_dandisets": ["000717"]}, "10101": {"acronym": "Pallidum", "name": "Pallidum", "color_hex_triplet": "C55252", "file_count": 0, "dandiset_count": 0, "dandisets": [], "total_file_count": 43, "total_dandiset_count": 1, "total_dandisets": ["000947"]}}